gabid/Binomialdistribution.py
gabid/Gaussiandistribution.py
gabid/Generaldistribution.py
gabid/__init__.py
gabid-0.6.dist-info/LICENSE
gabid-0.6.dist-info/METADATA
gabid-0.6.dist-info/WHEEL
gabid-0.6.dist-info/top_level.txt
gabid-0.6.dist-info/RECORD
