Metadata-Version: 2.1
Name: gabid
Version: 0.6
Summary: Gaussian and Binomial distributions
Home-page: UNKNOWN
Author: Sara Garci
Author-email: s@saragarci.com
License: UNKNOWN
Platform: UNKNOWN
